diceware_utils/__init__.py
diceware_utils/dir.py
diceware_utils/generate.py
diceware_utils/modify.py
diceware_utils/policy.py
diceware_utils/wordlist.py
diceware_utils/database/leetspeak.yaml
diceware_utils/database/policy.yaml
diceware_utils/database/wordlist/aspell-cs.txt.xz
diceware_utils/database/wordlist/aspell-en.txt.xz
diceware_utils/database/wordlist/bip0039.txt.xz
diceware_utils/database/wordlist/cracklib-small.txt.xz
diceware_utils/database/wordlist/diceware.txt.xz
diceware_utils/database/wordlist/eff-long.txt.xz
diceware_utils/database/wordlist/eff-short.txt.xz
diceware_utils/database/wordlist/eff-short2.txt.xz
diceware_utils/database/wordlist/skey.txt.xz
diceware_utils-0.6.0.dist-info/METADATA
diceware_utils-0.6.0.dist-info/RECORD
diceware_utils-0.6.0.dist-info/WHEEL
diceware_utils-0.6.0.dist-info/top_level.txt
