Metadata-Version: 2.1
Name: diceware-utils
Version: 0.6.0
Summary: A collection of tools to make diceware passphrase conform with "password policy"
Home-page: https://github.com/patarapolw/diceware_utils
Author: Pacharapol Withayasakpunt
Author-email: patarapolw@gmail.com
License: MIT
Keywords: password leet leetspeak diceware
Platform: UNKNOWN
Classifier: Development Status :: 4 - Beta
Classifier: Environment :: Console
Classifier: Intended Audience :: Developers
Classifier: License :: OSI Approved :: MIT License
Classifier: Natural Language :: English
Classifier: Operating System :: OS Independent
Classifier: Programming Language :: Python :: 3.5
Classifier: Programming Language :: Python :: 3.6
Classifier: Topic :: Security
Classifier: Topic :: Security :: Cryptography
Provides-Extra: test
Requires-Dist: PyYAML
Provides-Extra: test
Requires-Dist: pytest; extra == 'test'
Requires-Dist: pytest-doctestplus; extra == 'test'
